setup.py
botha01_probability/Binomialdistribution.py
botha01_probability/Gaussiandistribution.py
botha01_probability/Generaldistribution.py
botha01_probability/__init__.py
botha01_probability.egg-info/PKG-INFO
botha01_probability.egg-info/SOURCES.txt
botha01_probability.egg-info/dependency_links.txt
botha01_probability.egg-info/not-zip-safe
botha01_probability.egg-info/top_level.txt